slacklogger/__main__.py
slacklogger/core.py
slacklogger/__init__.py
slacklogger-0.1.5.dist-info/METADATA
slacklogger-0.1.5.dist-info/DESCRIPTION.rst
slacklogger-0.1.5.dist-info/metadata.json
slacklogger-0.1.5.dist-info/entry_points.txt
slacklogger-0.1.5.dist-info/WHEEL
slacklogger-0.1.5.dist-info/top_level.txt
slacklogger-0.1.5.dist-info/RECORD
