Metadata-Version: 2.0
Name: slacklogger
Version: 0.1.5
Summary: logger/notifier module for slack
Home-page: https://github.com/paoloo/slacklogger
Author: Paolo Oliveira
Author-email: paolo@fisica.ufc.br
License: BSD License
Platform: UNKNOWN
Requires-Dist: pyOpenSSL (>=16.0.0)
Requires-Dist: websocket-client (>=0.37.0)
